Workbook

Sheet Instructions
A1: Manual Test Execution Workbook
A2: ClinicalEHRApplication — https://2set.com · generated from manual/TEST-CASES.md
B4: How to use this workbook
B5: 1. Fill in the yellow cells on the 'Run Info' sheet before you start.
B6: 2. Work through the 'Test Cases' sheet. Set Result for each case you run.
B7: 3. For every Fail, add a row to 'Defect Log' and put its ID in the Defect ID column.
B8: 4. 'Summary' updates itself from your results — do not type into it.
B9: 5. After a deploy, also complete the 'Regression Checklist' sheet.
B11: Which cells you edit
B12: YELLOW cells are yours to fill in: Run Info fields, and the Result, Notes, Defect ID,
B13: Tested By and Date columns on Test Cases, Defect Log and Regression Checklist.
B14: Everything else — IDs, steps, expected results, all of Summary — is generated or
B15: calculated. Overwriting it will not break the workbook, but your edit will be lost the
B16: next time the workbook is regenerated from TEST-CASES.md.
... B48: Example of a completed row
A49: ID | B49: Result | C49: Notes | D49: Defect ID | E49: Tested By | F49: Date
A50: CLM-006 | B50: Fail | C50: Summary total showed $213.00 but the two lines are $165.00 + $48.00 = $213.00 — matched. Re-tested after cache clear: passes. | D50: BUG-0007 | E50: J. Azim | F50: 2026-09-26

Sheet Run Info
A1: Test Run Information
A2: Fill in the yellow cells before you begin.
B4: Build / commit SHA | D4: From `git log --oneline -1` on the server.
B5: Environment URL | C5: https://2set.com | D5: Change if testing a local or staging instance.
B6: Is this production? | C6: Yes | D6: If Yes, do NOT run any case tagged WRITE.
B7: Test run start date | D7: YYYY-MM-DD
B8: Test run end date | D8: YYYY-MM-DD
B9: Tester name
B10: Test plan version | C10: 1.0 | D10: See manual/TEST-PLAN.md
B11: Browser / version | D11: e.g. Chrome 131
B12: Operating system
B13: Backup taken & size verified | D13: A 0-byte dump is not a backup. Required before any WRITE testing.
B15: Totals (calculated)
B16: Total cases in this plan | C16: =COUNTA('Test Cases'!A4:A146)
B17: Executed | C17: =COUNTA('Test Cases'!H4:H146)
B18: Pass | C18: =COUNTIF('Test Cases'!H4:H146,"Pass")
B19: Fail | C19: =COUNTIF('Test Cases'!H4:H146,"Fail")
B20: Blocked | C20: =COUNTIF('Test Cases'!H4:H146,"Blocked")
B21: N/A | C21: =COUNTIF('Test Cases'!H4:H146,"N/A")
B22: Not run | C22: =C16-C17
B23: Pass rate (of Pass + Fail) | C23: =IFERROR(C18/(C18+C19),"")
B24: P1 failures — release blockers | C24: =COUNTIFS('Test Cases'!C4:C146,"P1",'Test Cases'!H4:H146,"Fail")
B25: Defects raised | C25: =COUNTA('Defect Log'!A4:A103)
B27: Release recommendation
B28: =IF(C24>0,"DO NOT RELEASE — "&C24&" P1 case(s) failed",IF(C19>0,"REVIEW — "&C19&" non-P1 failure(s) present",IF(C22>0,"INCOMPLETE — "&C22&" case(s) not run","PASS — no failures recorded")))

Sheet Test Cases
A1: Test Cases
A2: 143 cases · set the Result column · yellow columns are yours to fill in
A3: ID | B3: Module | C3: Pri | D3: Tag | E3: Test case | F3: Steps | G3: Expected result | H3: Result | I3: Notes / actual result | J3: Defect ID | K3: Tested By | L3: Date
A4: AUTH-001 | B4: Authentication | C4: P1 | D4: READ-ONLY | E4: Sign in with valid credentials | F4: 1. Open the site 2. Enter a valid email and password 3. Sign in | G4: Either the dashboard loads, or an MFA prompt appears if enforcement is on. No raw error text.
A5: AUTH-002 | B5: Authentication | C5: P1 | D5: READ-ONLY | E5: Wrong password refused | F5: Enter a valid email with a wrong password | G5: "Invalid email or password". Stays on sign-in. No session.
A6: AUTH-003 | B6: Authentication | C6: P1 | D6: READ-ONLY | E6: Unknown account refused identically | F6: Enter an email with no account | G6: Exactly the same message as AUTH-002. A different message lets an attacker enumerate accounts.
A7: AUTH-004 | B7: Authentication | C7: P2 | D7: READ-ONLY | E7: Empty fields | F7: Leave email and/or password blank, submit | G7: Browser validation blocks submission; no request is sent.
A8: AUTH-005 | B8: Authentication | C8: P2 | D8: READ-ONLY | E8: Password masked by default | F8: Look at the password field | G8: Characters are dots. A Show/Hide toggle is available.
A9: AUTH-006 | B9: Authentication | C9: P2 | D9: READ-ONLY | E9: Show/Hide toggle | F9: Type a password, click Show, then Hide | G9: Text is revealed, then masked again.
A10: AUTH-007 | B10: Authentication | C10: P1 | D10: READ-ONLY | E10: No backend detail leaks | F10: Trigger a failed sign-in | G10: No pgx, postgres, sql, bcrypt, panic, or stack trace anywhere on screen.
A11: AUTH-008 | B11: Authentication | C11: P1 | D11: READ-ONLY | E11: Sign out ends the session | F11: Sign in, sign out, press Back | G11: Returns to sign-in. The application is not reachable by going back.
A12: AUTH-009 | B12: Authentication | C12: P1 | D12: READ-ONLY | E12: Session required for the API | F12: Sign out. In a new tab open /api/auth/me | G12: 401, not patient data.
A13: AUTH-010 | B13: Authentication | C13: P2 | D13: READ-ONLY | E13: Remember me | F13: Sign in with Remember me, close the tab, reopen | G13: Behaviour matches the checkbox state; a fresh session is required if unchecked.
A14: AUTH-011 | B14: Authentication | C14: P3 | D14: READ-ONLY | E14: Rapid repeated failures | F14: Enter a wrong password 10 times | G14: The application stays stable. Note whether any rate limiting exists.
A15: MFA-001 | B15: Multi-factor authentication | C15: P1 | D15: WRITE | E15: Enrolment | F15: Sign in on an account with MFA required and no enrolment | G15: A QR code and a manual key are offered.
... A141: A11Y-006 | B141: Accessibility | C141: P2 | D141: READ-ONLY | E141: Errors announced | F141: Trigger a validation error with a screen reader | G141: The message is announced, not only shown in colour.
A142: CB-001 | B142: Cross-browser and responsive | C142: P2 | D142: READ-ONLY | E142: Chrome / Edge | G142: Full functionality.
A143: CB-002 | B143: Cross-browser and responsive | C143: P2 | D143: READ-ONLY | E143: Firefox | G143: Full functionality; check the HCFA print dialog especially.
A144: CB-003 | B144: Cross-browser and responsive | C144: P3 | D144: READ-ONLY | E144: Safari | G144: Full functionality; @page handling differs — verify HCFA print.
A145: CB-004 | B145: Cross-browser and responsive | C145: P3 | D145: READ-ONLY | E145: 1366 × 768 | G145: Usable without horizontal scrolling.
A146: CB-005 | B146: Cross-browser and responsive | C146: P3 | D146: READ-ONLY | E146: Tablet, 1024 wide | G146: Claim workspace remains usable; side panels may stack.

Sheet Summary
A1: Summary
A2: Calculated from the Test Cases sheet. Do not type into this sheet.
A3: Module | B3: Total | C3: Pass | D3: Fail | E3: Blocked | F3: N/A | G3: Not run | H3: Pass rate
A4: Authentication | B4: =COUNTIF('Test Cases'!$B$4:$B$146,$A4) | C4: =COUNTIFS('Test Cases'!$B$4:$B$146,$A4,'Test Cases'!$H$4:$H$146,"Pass") | D4: =COUNTIFS('Test Cases'!$B$4:$B$146,$A4,'Test Cases'!$H$4:$H$146,"Fail") | E4: =COUNTIFS('Test Cases'!$B$4:$B$146,$A4,'Test Cases'!$H$4:$H$146,"Blocked") | F4: =COUNTIFS('Test Cases'!$B$4:$B$146,$A4,'Test Cases'!$H$4:$H$146,"N/A") | G4: =B4-C4-D4-E4-F4 | H4: =IFERROR(C4/(C4+D4),"")
A5: Multi-factor authentication | B5: =COUNTIF('Test Cases'!$B$4:$B$146,$A5) | C5: =COUNTIFS('Test Cases'!$B$4:$B$146,$A5,'Test Cases'!$H$4:$H$146,"Pass") | D5: =COUNTIFS('Test Cases'!$B$4:$B$146,$A5,'Test Cases'!$H$4:$H$146,"Fail") | E5: =COUNTIFS('Test Cases'!$B$4:$B$146,$A5,'Test Cases'!$H$4:$H$146,"Blocked") | F5: =COUNTIFS('Test Cases'!$B$4:$B$146,$A5,'Test Cases'!$H$4:$H$146,"N/A") | G5: =B5-C5-D5-E5-F5 | H5: =IFERROR(C5/(C5+D5),"")
A6: Roles and permissions | B6: =COUNTIF('Test Cases'!$B$4:$B$146,$A6) | C6: =COUNTIFS('Test Cases'!$B$4:$B$146,$A6,'Test Cases'!$H$4:$H$146,"Pass") | D6: =COUNTIFS('Test Cases'!$B$4:$B$146,$A6,'Test Cases'!$H$4:$H$146,"Fail") | E6: =COUNTIFS('Test Cases'!$B$4:$B$146,$A6,'Test Cases'!$H$4:$H$146,"Blocked") | F6: =COUNTIFS('Test Cases'!$B$4:$B$146,$A6,'Test Cases'!$H$4:$H$146,"N/A") | G6: =B6-C6-D6-E6-F6 | H6: =IFERROR(C6/(C6+D6),"")
A7: Patients | B7: =COUNTIF('Test Cases'!$B$4:$B$146,$A7) | C7: =COUNTIFS('Test Cases'!$B$4:$B$146,$A7,'Test Cases'!$H$4:$H$146,"Pass") | D7: =COUNTIFS('Test Cases'!$B$4:$B$146,$A7,'Test Cases'!$H$4:$H$146,"Fail") | E7: =COUNTIFS('Test Cases'!$B$4:$B$146,$A7,'Test Cases'!$H$4:$H$146,"Blocked") | F7: =COUNTIFS('Test Cases'!$B$4:$B$146,$A7,'Test Cases'!$H$4:$H$146,"N/A") | G7: =B7-C7-D7-E7-F7 | H7: =IFERROR(C7/(C7+D7),"")
A8: Billing ledger and payment posting | B8: =COUNTIF('Test Cases'!$B$4:$B$146,$A8) | C8: =COUNTIFS('Test Cases'!$B$4:$B$146,$A8,'Test Cases'!$H$4:$H$146,"Pass") | D8: =COUNTIFS('Test Cases'!$B$4:$B$146,$A8,'Test Cases'!$H$4:$H$146,"Fail") | E8: =COUNTIFS('Test Cases'!$B$4:$B$146,$A8,'Test Cases'!$H$4:$H$146,"Blocked") | F8: =COUNTIFS('Test Cases'!$B$4:$B$146,$A8,'Test Cases'!$H$4:$H$146,"N/A") | G8: =B8-C8-D8-E8-F8 | H8: =IFERROR(C8/(C8+D8),"")
A9: Claims and the claim workspace | B9: =COUNTIF('Test Cases'!$B$4:$B$146,$A9) | C9: =COUNTIFS('Test Cases'!$B$4:$B$146,$A9,'Test Cases'!$H$4:$H$146,"Pass") | D9: =COUNTIFS('Test Cases'!$B$4:$B$146,$A9,'Test Cases'!$H$4:$H$146,"Fail") | E9: =COUNTIFS('Test Cases'!$B$4:$B$146,$A9,'Test Cases'!$H$4:$H$146,"Blocked") | F9: =COUNTIFS('Test Cases'!$B$4:$B$146,$A9,'Test Cases'!$H$4:$H$146,"N/A") | G9: =B9-C9-D9-E9-F9 | H9: =IFERROR(C9/(C9+D9),"")
A10: CMS-1500 / HCFA | B10: =COUNTIF('Test Cases'!$B$4:$B$146,$A10) | C10: =COUNTIFS('Test Cases'!$B$4:$B$146,$A10,'Test Cases'!$H$4:$H$146,"Pass") | D10: =COUNTIFS('Test Cases'!$B$4:$B$146,$A10,'Test Cases'!$H$4:$H$146,"Fail") | E10: =COUNTIFS('Test Cases'!$B$4:$B$146,$A10,'Test Cases'!$H$4:$H$146,"Blocked") | F10: =COUNTIFS('Test Cases'!$B$4:$B$146,$A10,'Test Cases'!$H$4:$H$146,"N/A") | G10: =B10-C10-D10-E10-F10 | H10: =IFERROR(C10/(C10+D10),"")
A11: Medical records | B11: =COUNTIF('Test Cases'!$B$4:$B$146,$A11) | C11: =COUNTIFS('Test Cases'!$B$4:$B$146,$A11,'Test Cases'!$H$4:$H$146,"Pass") | D11: =COUNTIFS('Test Cases'!$B$4:$B$146,$A11,'Test Cases'!$H$4:$H$146,"Fail") | E11: =COUNTIFS('Test Cases'!$B$4:$B$146,$A11,'Test Cases'!$H$4:$H$146,"Blocked") | F11: =COUNTIFS('Test Cases'!$B$4:$B$146,$A11,'Test Cases'!$H$4:$H$146,"N/A") | G11: =B11-C11-D11-E11-F11 | H11: =IFERROR(C11/(C11+D11),"")
A12: Prescriptions (Rx) | B12: =COUNTIF('Test Cases'!$B$4:$B$146,$A12) | C12: =COUNTIFS('Test Cases'!$B$4:$B$146,$A12,'Test Cases'!$H$4:$H$146,"Pass") | D12: =COUNTIFS('Test Cases'!$B$4:$B$146,$A12,'Test Cases'!$H$4:$H$146,"Fail") | E12: =COUNTIFS('Test Cases'!$B$4:$B$146,$A12,'Test Cases'!$H$4:$H$146,"Blocked") | F12: =COUNTIFS('Test Cases'!$B$4:$B$146,$A12,'Test Cases'!$H$4:$H$146,"N/A") | G12: =B12-C12-D12-E12-F12 | H12: =IFERROR(C12/(C12+D12),"")
A13: Reports, backup, and audit | B13: =COUNTIF('Test Cases'!$B$4:$B$146,$A13) | C13: =COUNTIFS('Test Cases'!$B$4:$B$146,$A13,'Test Cases'!$H$4:$H$146,"Pass") | D13: =COUNTIFS('Test Cases'!$B$4:$B$146,$A13,'Test Cases'!$H$4:$H$146,"Fail") | E13: =COUNTIFS('Test Cases'!$B$4:$B$146,$A13,'Test Cases'!$H$4:$H$146,"Blocked") | F13: =COUNTIFS('Test Cases'!$B$4:$B$146,$A13,'Test Cases'!$H$4:$H$146,"N/A") | G13: =B13-C13-D13-E13-F13 | H13: =IFERROR(C13/(C13+D13),"")
A14: Demo account | B14: =COUNTIF('Test Cases'!$B$4:$B$146,$A14) | C14: =COUNTIFS('Test Cases'!$B$4:$B$146,$A14,'Test Cases'!$H$4:$H$146,"Pass") | D14: =COUNTIFS('Test Cases'!$B$4:$B$146,$A14,'Test Cases'!$H$4:$H$146,"Fail") | E14: =COUNTIFS('Test Cases'!$B$4:$B$146,$A14,'Test Cases'!$H$4:$H$146,"Blocked") | F14: =COUNTIFS('Test Cases'!$B$4:$B$146,$A14,'Test Cases'!$H$4:$H$146,"N/A") | G14: =B14-C14-D14-E14-F14 | H14: =IFERROR(C14/(C14+D14),"")
A15: Accessibility | B15: =COUNTIF('Test Cases'!$B$4:$B$146,$A15) | C15: =COUNTIFS('Test Cases'!$B$4:$B$146,$A15,'Test Cases'!$H$4:$H$146,"Pass") | D15: =COUNTIFS('Test Cases'!$B$4:$B$146,$A15,'Test Cases'!$H$4:$H$146,"Fail") | E15: =COUNTIFS('Test Cases'!$B$4:$B$146,$A15,'Test Cases'!$H$4:$H$146,"Blocked") | F15: =COUNTIFS('Test Cases'!$B$4:$B$146,$A15,'Test Cases'!$H$4:$H$146,"N/A") | G15: =B15-C15-D15-E15-F15 | H15: =IFERROR(C15/(C15+D15),"")
A16: Cross-browser and responsive | B16: =COUNTIF('Test Cases'!$B$4:$B$146,$A16) | C16: =COUNTIFS('Test Cases'!$B$4:$B$146,$A16,'Test Cases'!$H$4:$H$146,"Pass") | D16: =COUNTIFS('Test Cases'!$B$4:$B$146,$A16,'Test Cases'!$H$4:$H$146,"Fail") | E16: =COUNTIFS('Test Cases'!$B$4:$B$146,$A16,'Test Cases'!$H$4:$H$146,"Blocked") | F16: =COUNTIFS('Test Cases'!$B$4:$B$146,$A16,'Test Cases'!$H$4:$H$146,"N/A") | G16: =B16-C16-D16-E16-F16 | H16: =IFERROR(C16/(C16+D16),"")
A17: TOTAL | B17: =SUM(B4:B16) | C17: =SUM(C4:C16) | D17: =SUM(D4:D16) | E17: =SUM(E4:E16) | F17: =SUM(F4:F16) | G17: =SUM(G4:G16) | H17: =IFERROR(C17/(C17+D17),"")
A19: By priority
A20: Priority | B20: Total | C20: Pass | D20: Fail | E20: Blocked | F20: N/A | G20: Not run | H20: Pass rate
A21: P1 | B21: =COUNTIF('Test Cases'!$C$4:$C$146,$A21) | C21: =COUNTIFS('Test Cases'!$C$4:$C$146,$A21,'Test Cases'!$H$4:$H$146,"Pass") | D21: =COUNTIFS('Test Cases'!$C$4:$C$146,$A21,'Test Cases'!$H$4:$H$146,"Fail") | E21: =COUNTIFS('Test Cases'!$C$4:$C$146,$A21,'Test Cases'!$H$4:$H$146,"Blocked") | F21: =COUNTIFS('Test Cases'!$C$4:$C$146,$A21,'Test Cases'!$H$4:$H$146,"N/A") | G21: =B21-C21-D21-E21-F21 | H21: =IFERROR(C21/(C21+D21),"")
A22: P2 | B22: =COUNTIF('Test Cases'!$C$4:$C$146,$A22) | C22: =COUNTIFS('Test Cases'!$C$4:$C$146,$A22,'Test Cases'!$H$4:$H$146,"Pass") | D22: =COUNTIFS('Test Cases'!$C$4:$C$146,$A22,'Test Cases'!$H$4:$H$146,"Fail") | E22: =COUNTIFS('Test Cases'!$C$4:$C$146,$A22,'Test Cases'!$H$4:$H$146,"Blocked") | F22: =COUNTIFS('Test Cases'!$C$4:$C$146,$A22,'Test Cases'!$H$4:$H$146,"N/A") | G22: =B22-C22-D22-E22-F22 | H22: =IFERROR(C22/(C22+D22),"")
A23: P3 | B23: =COUNTIF('Test Cases'!$C$4:$C$146,$A23) | C23: =COUNTIFS('Test Cases'!$C$4:$C$146,$A23,'Test Cases'!$H$4:$H$146,"Pass") | D23: =COUNTIFS('Test Cases'!$C$4:$C$146,$A23,'Test Cases'!$H$4:$H$146,"Fail") | E23: =COUNTIFS('Test Cases'!$C$4:$C$146,$A23,'Test Cases'!$H$4:$H$146,"Blocked") | F23: =COUNTIFS('Test Cases'!$C$4:$C$146,$A23,'Test Cases'!$H$4:$H$146,"N/A") | G23: =B23-C23-D23-E23-F23 | H23: =IFERROR(C23/(C23+D23),"")
A25: Exit criteria
A26: All P1 cases pass | B26: =IF(D21>0,"NOT MET — "&D21&" P1 failure(s)",IF(G21>0,"INCOMPLETE — "&G21&" P1 case(s) not run","MET"))
A27: No unexplained failures anywhere | B27: =IF(D17>0,"REVIEW — "&D17&" failure(s) recorded","MET")
A28: Every case accounted for | B28: =IF(G17>0,"INCOMPLETE — "&G17&" case(s) not run","MET")

Sheet Defect Log
A1: Defect Log
A2: One row per defect. Put the ID back in the Test Cases 'Defect ID' column.
A3: Defect ID | B3: Test case ID | C3: Title | D3: Module | E3: Severity | F3: Priority | G3: Steps to reproduce | H3: Expected | I3: Actual | J3: Status | K3: Raised by

Sheet Regression Checklist
A1: Post-Deploy Regression Checklist
A2: Run after every deploy. About 30 minutes. Everything here is read-only and safe on production.
A3: # | B3: Section | C3: Check | D3: Expected | E3: Result | F3: Notes
A4: A1 | B4: A. Deploy landed | C4: Backup exists and is not empty (ls -lh ~/medbill-*.dump) | D4: Size in MB. A 0-byte file is not a backup.
A5: A2 | B5: A. Deploy landed | C5: The commit moved (git log --oneline -1) | D5: The SHA you intended to deploy
A6: A3 | B6: A. Deploy landed | C6: Containers are up (docker ps) | D6: db, api and web all running
A7: A4 | B7: A. Deploy landed | C7: The bundle is new (npm run test:smoke) | D7: 7 passed, including the stale-bundle check
A8: B1 | B8: B. No data loss | C8: Row counts unchanged vs before the deploy | D8: diff of before/after counts is empty
A9: B2 | B9: B. No data loss | C9: Password hashes unchanged | D9: diff of before/after user hashes is empty
A10: B3 | B10: B. No data loss | C10: MFA enrolments intact | D10: user_mfa count unchanged
A11: B4 | B11: B. No data loss | C11: Trusted devices intact | D11: trusted_devices count unchanged
A12: B5 | B12: B. No data loss | C12: The release's new tables exist | D12: Present in the database
A13: C1 | B13: C. Authentication | C13: Sign in with a valid account | D13: Reaches the application
A14: C2 | B14: C. Authentication | C14: Wrong password | D14: Refused, generic message, no stack trace
A15: C3 | B15: C. Authentication | C15: MFA behaves as configured | D15: Matches the intended MFA_ENFORCEMENT
... A40: G7 | B40: G. Claims & CMS-1500 | C40: Alignment controls and test page available | D40: Present
B42: Checks passed | C42: =COUNTIF(E4:E40,"Pass")&" of "&37
B43: Checks failed | C43: =COUNTIF(E4:E40,"Fail")
B44: Verdict | C44: =IF(COUNTIF(E4:E40,"Fail")>0,"FAIL — sections B, C, E and F are release blockers; consider rolling back",IF(COUNTA(E4:E40)<37,"INCOMPLETE","PASS"))
